[
    {
        "name": "id",
        "dbType": "increments",
        "htmlType": "",
        "validations": "",
        "searchable": false,
        "fillable": false,
        "primary": true,
        "inForm": false,
        "inIndex": false
    },
    {
        "name": "titulo",
        "dbType": "string",
        "htmlType": "text"
    },
    {
        "name": "ordem",
        "dbType": "integer",
        "htmlType": "numeric"
    },
    {
        "name": "url",
        "dbType": "string",
        "htmlType": "text"
    },
    {
        "name": "created_at",
        "dbType": "timestamp",
        "htmlType": "",
        "validations": "",
        "searchable": false,
        "fillable": false,
        "primary": false,
        "inForm": false,
        "inIndex": false
    },
    {
        "name": "updated_at",
        "dbType": "timestamp",
        "htmlType": "",
        "validations": "",
        "searchable": false,
        "fillable": false,
        "primary": false,
        "inForm": false,
        "inIndex": false
    }
]
